shiv/__init__.py
shiv/__main__.py
shiv/__version__.py
shiv/builder.py
shiv/cli.py
shiv/constants.py
shiv/info.py
shiv/pip.py
shiv/bootstrap/__init__.py
shiv/bootstrap/environment.py
shiv/bootstrap/filelock.py
shiv/bootstrap/interpreter.py
shiv-1.0.8.dist-info/LICENSE
shiv-1.0.8.dist-info/METADATA
shiv-1.0.8.dist-info/WHEEL
shiv-1.0.8.dist-info/entry_points.txt
shiv-1.0.8.dist-info/top_level.txt
shiv-1.0.8.dist-info/RECORD
