Metadata-Version: 2.1
Name: shiv
Version: 1.0.8
Summary: A command line utility for building fully self contained Python zipapps.
Home-page: https://github.com/linkedin/shiv
Author: Loren Carvalho
Author-email: loren@linkedin.com
License: BSD License
Classifier: License :: OSI Approved :: BSD License
Classifier: Programming Language :: Python :: 3 :: Only
Classifier: Programming Language :: Python :: 3
Classifier: Programming Language :: Python :: 3.8
Classifier: Programming Language :: Python :: 3.9
Classifier: Programming Language :: Python :: 3.10
Classifier: Programming Language :: Python :: 3.11
Requires-Python: >=3.6
License-File: LICENSE
Requires-Dist: click!=7.0,>=6.7
Requires-Dist: pip>=9.0.3
Requires-Dist: setuptools
Requires-Dist: importlib_resources; python_version < "3.7"
Provides-Extra: rtd
Requires-Dist: sphinx-click; extra == "rtd"
